LICENSE
MANIFEST.in
README.rst
requirements.txt
setup.cfg
setup.py
contrib/iseeyou.service
contrib/peekaboo.service
etc/iseeyou.conf
etc/peekaboo-docker.conf
etc/peekaboo.conf
peekaboo.egg-info/PKG-INFO
peekaboo.egg-info/SOURCES.txt
peekaboo.egg-info/dependency_links.txt
peekaboo.egg-info/requires.txt
peekaboo.egg-info/top_level.txt
plugins/info/cpu_info.py
plugins/info/display_info.py
plugins/info/dmi_info.py
plugins/info/host_info.py
plugins/info/mem_info.py
plugins/info/network_info.py
plugins/info/os_info.py
plugins/info/virtual_info.py
plugins/status/cpu_status.py
plugins/status/disk_status.py
plugins/status/mem_status.py
plugins/status/system_status.py
scripts/peekaboo