Metadata-Version: 1.1
Name: peekaboo
Version: 0.8.5
Summary: Expose hardware info through HTTP
Home-page: https://github.com/mickep76/peekaboo.git
Author: Michael Persson
Author-email: michael.ake.persson@gmail.com
License: Apache License, Version 2.0
Platform: UNKNOWN
Classifier: Development Status :: 5 - Production/Stable
Classifier: Environment :: Console
Classifier: Intended Audience :: System Administrators
Classifier: License :: OSI Approved :: Apache Software License
Classifier: Operating System :: POSIX :: Linux
